helloworld.py
abhkumar10_helloworld-0.0.3.dist-info/LICENSE.txt
abhkumar10_helloworld-0.0.3.dist-info/METADATA
abhkumar10_helloworld-0.0.3.dist-info/WHEEL
abhkumar10_helloworld-0.0.3.dist-info/top_level.txt
abhkumar10_helloworld-0.0.3.dist-info/RECORD
